sonarr/__init__.py
sonarr/__version__.py
sonarr/client.py
sonarr/const.py
sonarr/exceptions.py
sonarr/models.py
sonarr/sonarr.py
sonarr-0.3.0.dist-info/LICENSE
sonarr-0.3.0.dist-info/METADATA
sonarr-0.3.0.dist-info/WHEEL
sonarr-0.3.0.dist-info/top_level.txt
sonarr-0.3.0.dist-info/RECORD
