Metadata-Version: 2.1
Name: sonarr
Version: 0.3.0
Summary: Asynchronous Python client for the Sonarr API.
Home-page: https://github.com/ctalkington/python-sonarr
Author: Chris Talkington
Author-email: chris@talkingtontech.com
License: MIT license
Keywords: sonarr,api,async,client
Platform: UNKNOWN
Classifier: Development Status :: 4 - Beta
Classifier: Framework :: AsyncIO
Classifier: Intended Audience :: Developers
Classifier: License :: OSI Approved :: MIT License
Classifier: Natural Language :: English
Classifier: Programming Language :: Python :: 3.7
Classifier: Programming Language :: Python :: 3.8
Classifier: Programming Language :: Python :: 3
Classifier: Topic :: Software Development :: Libraries :: Python Modules
Requires-Dist: aiohttp (>=3.6.2)
Requires-Dist: yarl (>=1.4.2)
